timetracker/__init__.py
timetracker/cli.py
timetracker/consts.py
timetracker/csvfile.py
timetracker/csvget.py
timetracker/csvold.py
timetracker/csvrun.py
timetracker/csvutils.py
timetracker/docx.py
timetracker/msgs.py
timetracker/ntcsv.py
timetracker/proc.py
timetracker/recorder.py
timetracker/report.py
timetracker/starttime.py
timetracker/utils.py
timetracker/cfg/__init__.py
timetracker/cfg/cfg.py
timetracker/cfg/cfg_global.py
timetracker/cfg/cfg_local.py
timetracker/cfg/doc_local.py
timetracker/cfg/docutils.py
timetracker/cfg/finder.py
timetracker/cfg/tomutils.py
timetracker/cfg/utils.py
timetracker/cmd/__init__.py
timetracker/cmd/activity.py
timetracker/cmd/cancel.py
timetracker/cmd/common.py
timetracker/cmd/csv.py
timetracker/cmd/fncs.py
timetracker/cmd/hours.py
timetracker/cmd/init.py
timetracker/cmd/invoice.py
timetracker/cmd/none.py
timetracker/cmd/paid.py
timetracker/cmd/projects.py
timetracker/cmd/report.py
timetracker/cmd/running.py
timetracker/cmd/start.py
timetracker/cmd/stop.py
timetracker/cmd/tag.py
timetracker/epoch/__init__.py
timetracker/epoch/calc.py
timetracker/epoch/epoch.py
timetracker/epoch/stmach.py
timetracker/epoch/text.py
timetracker/epoch/cli/__init__.py
timetracker/epoch/cli/calc.py
timetracker/epoch/cli/timestr.py
timetracker_csv-0.8.6.dist-info/licenses/LICENSE
timetracker_csv-0.8.6.dist-info/METADATA
timetracker_csv-0.8.6.dist-info/WHEEL
timetracker_csv-0.8.6.dist-info/entry_points.txt
timetracker_csv-0.8.6.dist-info/top_level.txt
timetracker_csv-0.8.6.dist-info/RECORD
