Metadata-Version: 2.4
Name: timetracker-csv
Version: 0.8.6
Summary: Pandas-friendly time tracking from the CLI
Author-email: "DV Klopfenstein, PhD" <dvklopfenstein@protonmail.com>
License-Expression: AGPL-3.0-or-later
Project-URL: Homepage, https://github.com/dvklopfenstein/timetracker
Project-URL: Issues, https://github.com/dvklopfenstein/timetracker/issues
Project-URL: Changelog, https://github.com/dvklopfenstein/timetracker/blob/main/CHANGELOG.md
Project-URL: Documentation, https://dvklopfenstein.github.io/timetracker/
Project-URL: PiPy, https://pypi.org/project/timetracker-csv/
Keywords: Linux,cli,productivity,csv,history,collaboration,pandas,time-tracker,timetracker,csv-reading,csv-export,timetracking
Classifier: Intended Audience :: Science/Research
Classifier: Intended Audience :: Developers
Classifier: Intended Audience :: End Users/Desktop
Classifier: Topic :: Office/Business :: Financial :: Spreadsheet
Classifier: Topic :: Office/Business :: News/Diary
Classifier: Topic :: Office/Business :: Scheduling
Classifier: Topic :: Scientific/Engineering
Classifier: Programming Language :: Python
Classifier: Environment :: Console
Classifier: Development Status :: 5 - Production/Stable
Classifier: Programming Language :: Python :: 3.9
Classifier: Programming Language :: Python :: 3.10
Classifier: Programming Language :: Python :: 3.11
Classifier: Programming Language :: Python :: 3.12
Classifier: Programming Language :: Python :: 3.13
Classifier: Operating System :: POSIX :: Linux
Classifier: Operating System :: POSIX
Classifier: Operating System :: Unix
Classifier: Operating System :: MacOS
Requires-Python: >=3.8
License-File: LICENSE
Requires-Dist: tomlkit
Requires-Dist: pytimeparse2
Requires-Dist: dateparser
Dynamic: license-file
